doxytag2zealdb/CONTRIBUTORS
doxytag2zealdb/COPYING
doxytag2zealdb/README.md
doxytag2zealdb/__about__.py
doxytag2zealdb/__init__.py
doxytag2zealdb/__main__.py
doxytag2zealdb/doxytag.py
doxytag2zealdb/doxytag2zealdb.py
doxytag2zealdb/doxytagfile.py
doxytag2zealdb/propertylist.py
doxytag2zealdb/zealdb.py
doxytag2zealdb-0.3.1.dist-info/COPYING
doxytag2zealdb-0.3.1.dist-info/METADATA
doxytag2zealdb-0.3.1.dist-info/WHEEL
doxytag2zealdb-0.3.1.dist-info/entry_points.txt
doxytag2zealdb-0.3.1.dist-info/top_level.txt
doxytag2zealdb-0.3.1.dist-info/RECORD
