Metadata-Version: 2.1
Name: doxytag2zealdb
Version: 0.3.1
Summary: doxytag2zealdb creates a SQLite3 database from a Doxygen tag
Home-page: https://gitlab.com/vedvyas/doxytag2zealdb
Author: Ved Vyas
Author-email: ved@vyas.io
License: GPLv3+
Download-URL: https://gitlab.com/vedvyas/doxytag2zealdb/repository/archive.tar.bz2?ref=v0.3.1
Keywords: Zeal Dash Doxygen SQLite3
Platform: UNKNOWN
Classifier: Development Status :: 4 - Beta
Classifier: Intended Audience :: Developers
Classifier: Topic :: Software Development :: Documentation
Classifier: License :: OSI Approved :: GNU General Public License v3 or later (GPLv3+)
Classifier: Programming Language :: Python :: 2
Classifier: Programming Language :: Python :: 2.7
Classifier: Programming Language :: Python :: 3
Requires-Dist: docopt (>=0.6.2)
Requires-Dist: lxml (>=3.6.0)
Requires-Dist: beautifulsoup4 (>=4.4.1)
Requires-Dist: future
